setup.cfg
setup.py
uploader_clients.py
uploader_login_page.py
uploader_rules.py
Auth0_ci.egg-info/PKG-INFO
Auth0_ci.egg-info/SOURCES.txt
Auth0_ci.egg-info/dependency_links.txt
Auth0_ci.egg-info/requires.txt
Auth0_ci.egg-info/top_level.txt