Metadata-Version: 1.1
Name: Auth0-ci
Version: 1.0.2
Summary: Super simple CI scripts for Auth0
Home-page: https://github.com/mozilla-iam/auth0-ci
Author: Guillaume Destuynder
Author-email: gdestuynder@mozilla.com
License: MPL
Keywords: auth0 ci deploy
Platform: UNKNOWN
Classifier: Development Status :: 5 - Production/Stable
Classifier: License :: OSI Approved :: Mozilla Public License 2.0 (MPL 2.0)
